drcheck/__init__.py
drcheck/__version__.py
drcheck/analysis.py
drcheck/audio.py
drcheck/cli.py
drcheck/formatters.py
drcheck/parallel.py
drcheck-1.1.1.dist-info/METADATA
drcheck-1.1.1.dist-info/WHEEL
drcheck-1.1.1.dist-info/entry_points.txt
drcheck-1.1.1.dist-info/licenses/LICENSE
drcheck-1.1.1.dist-info/RECORD
