Metadata-Version: 2.4
Name: drcheck
Version: 1.1.1
Summary: Dynamic Range Analyzer - Fight the Loudness War
Project-URL: Homepage, https://github.com/nixternal/drcheck
Project-URL: Repository, https://github.com/nixternal/drcheck
Project-URL: Issues, https://github.com/nixternal/drcheck/issues
Project-URL: Documentation, https://github.com/nixternal/drcheck#readme
Author-email: Rich Johnson <nixternal@gmail.com>
License: GPL-3.0-or-later
License-File: LICENSE
Keywords: analysis,audio,dr14,dynamic-range,loudness-war,music
Classifier: Development Status :: 5 - Production/Stable
Classifier: Intended Audience :: End Users/Desktop
Classifier: License :: OSI Approved :: GNU General Public License v3 or later (GPLv3+)
Classifier: Programming Language :: Python :: 3
Classifier: Programming Language :: Python :: 3.10
Classifier: Programming Language :: Python :: 3.11
Classifier: Programming Language :: Python :: 3.12
Classifier: Programming Language :: Python :: 3.13
Classifier: Topic :: Multimedia :: Sound/Audio :: Analysis
Requires-Python: >=3.10
Requires-Dist: click>=8.1.0
Requires-Dist: mutagen>=1.47.0
Requires-Dist: numpy>=1.24.0
Requires-Dist: soundfile>=0.12.0
Provides-Extra: dev
Requires-Dist: pytest-cov>=4.0.0; extra == 'dev'
Requires-Dist: pytest>=7.0.0; extra == 'dev'
Provides-Extra: html
Requires-Dist: pillow>=12.1.0; extra == 'html'
Provides-Extra: lossy
Requires-Dist: pydub>=0.25.1; extra == 'lossy'
